[
  {
    "headline": "The US vs. Apple: Does the FBI Have a Case?",
    "src": "Fortune"
  },
  {
    "headline": "Donald Trump says he'll win independents and New York state. The numbers don't.",
    "src": "Washington Post"
  },
  {
    "headline": "Sandra Day O'Connor: Obama should name Scalia's replacement",
    "src": "CNN"
  },
  {
    "headline": "President confirms it: I'm going to Cuba",
    "src": "Miami Herald"
  },
  {
    "headline": "Turkey blames Kurdish militants for Ankara bomb, vows response in Syria and Iraq",
    "src": "Reuters"
  },
  {
    "headline": "'Mob Wives' star Angela 'Big Ang' Raiola dies at 55",
    "src": "USA TODAY"
  },
  {
    "headline": "What's at Stake as Britain and EU Discuss How to Maintain a Union",
    "src": "New York Times"
  },
  {
    "headline": "Pope Francis, Illegal Immigration And Border Security: How Mexico Became Tougher Than The United States On ...",
    "src": "International Business Times"
  },
  {
    "headline": "South Korea mulls next steps against nuclear-armed North",
    "src": "Worcester Telegram"
  },
  {
    "headline": "Ghana: 53 Killed as Bus Collides With Tomato Truck",
    "src": "New York Times"
  },
  {
    "headline": "Serial stowaway arrested at O'Hare",
    "src": "Chicago Sun-Times"
  },
  {
    "headline": "The Latest: California storm packing wind, rain moves south",
    "src": "seattlepi.com"
  },
  {
    "headline": "Former US marine attacked at McDonald's. Was it racially motivated?",
    "src": "Christian Science Monitor"
  },
  {
    "headline": "Officers describe thwarted attack at Texas cartoon contest",
    "src": "Fox News"
  },
  {
    "headline": "Walmart's Q4 income down 7.9% as sales fall, lowers outlook",
    "src": "USA TODAY"
  },
  {
    "headline": "OECD urges world leaders to tackle flagging growth",
    "src": "Reuters"
  },
  {
    "headline": "IBM Acquiring Truven Health Analytics For $2.6 Billion And Adding It To Watson Health",
    "src": "TechCrunch"
  },
  {
    "headline": "China urges impartial handling of issue concerning ICBC Madrid offices",
    "src": "Xinhua"
  },
  {
    "headline": "Microsoft updates Translator with AI-powered offline translation on Android, OCR support on iOS",
    "src": "VentureBeat"
  },
  {
    "headline": "No One Should Ever Pay to Remove a Bitcoin Ransomware Infection",
    "src": "newsBTC"
  },
  {
    "headline": "Nextbit Robin review: a smartphone in the clouds",
    "src": "The Verge"
  },
  {
    "headline": "Apple Pay takes on China's Internet kings in mobile payments",
    "src": "VentureBeat"
  },
  {
    "headline": "Kanye West Backstage 'SNL' Meltdown Leaked",
    "src": "ABC News"
  },
  {
    "headline": "Stephan James, 'Race' revisit Jesse Owens' legacy",
    "src": "USA TODAY"
  },
  {
    "headline": "Jury acquits Ohio man of stalking Gwyneth Paltrow",
    "src": "Washington Post"
  },
  {
    "headline": "Adele Admits to Her Own Pitchiness After 2016 Grammys Mic Mishap: \"It's Emotion!\"",
    "src": "E! Online"
  },
  {
    "headline": "NBA Trade Deadline 2016: End Time, Latest Rumors and Predictions",
    "src": "Bleacher Report"
  },
  {
    "headline": "North Carolina saddled with bad loss to Duke because it still can't finish",
    "src": "Sporting News"
  },
  {
    "headline": "Ryan McDonagh returns, but Blackhawks' power play and Artemi Panarin sink Rangers",
    "src": "New York Daily News"
  },
  {
    "headline": "Report: Howard and Harden 'maneuvered' to have the other traded",
    "src": "CBSSports.com"
  },
  {
    "headline": "Interbreeding: Neanderthals and modern humans mated 50000 years before we thought",
    "src": "Christian Science Monitor"
  },
  {
    "headline": "Where do asteroids go to die?",
    "src": "Christian Science Monitor"
  },
  {
    "headline": "This beautiful new map of Mars makes it look like a great place for hiking",
    "src": "Washington Post"
  },
  {
    "headline": "IBM, XPrize Announce Artificial Intelligence Competition With $5 Million Prize Money",
    "src": "International Business Times"
  },
  {
    "headline": "Colombia's forecast on Zika-linked birth defect may be too high, health minister says",
    "src": "Fox News"
  },
  {
    "headline": "Testosterone gel is no fountain of youth, study finds",
    "src": "Fox News"
  },
  {
    "headline": "Diabetes Drug May Help Prevent Heart Attack, Recurring Stroke",
    "src": "Tech Times"
  },
  {
    "headline": "FDA likely underestimated fetal deaths from Essure: analyst",
    "src": "Fox News"
  }
]